AppiumLibrary/__init__.py
AppiumLibrary/version.py
AppiumLibrary/keywords/__init__.py
AppiumLibrary/keywords/_android_utils.py
AppiumLibrary/keywords/_applicationmanagement.py
AppiumLibrary/keywords/_element.py
AppiumLibrary/keywords/_keyevent.py
AppiumLibrary/keywords/_logging.py
AppiumLibrary/keywords/_mobilekeywords.py
AppiumLibrary/keywords/_runonfailure.py
AppiumLibrary/keywords/_screenshot.py
AppiumLibrary/keywords/_touch.py
AppiumLibrary/keywords/_waiting.py
AppiumLibrary/keywords/keywordgroup.py
AppiumLibrary/locators/__init__.py
AppiumLibrary/locators/elementfinder.py
AppiumLibrary/utils/__init__.py
AppiumLibrary/utils/applicationcache.py
AppiumLibrary/utils/librarylistener.py
AppiumLibrary/utils/events/__init__.py
AppiumLibrary/utils/events/event.py
AppiumLibrary/utils/events/scope_event.py
robotframework_mobilelibrary-2.0.6.dev1.dist-info/top_level.txt
robotframework_mobilelibrary-2.0.6.dev1.dist-info/pbr.json
robotframework_mobilelibrary-2.0.6.dev1.dist-info/METADATA
robotframework_mobilelibrary-2.0.6.dev1.dist-info/DESCRIPTION.rst
robotframework_mobilelibrary-2.0.6.dev1.dist-info/metadata.json
robotframework_mobilelibrary-2.0.6.dev1.dist-info/WHEEL
robotframework_mobilelibrary-2.0.6.dev1.dist-info/RECORD
