Metadata-Version: 2.0
Name: robotframework-mobilelibrary
Version: 2.0.6.dev1
Summary: app testing library for Robot Framework Extended with AppiumLibrary
Home-page: https://github.com/Netease-AutoTest/robotframework-mobilelibrary
Author: Subscription QA
Author-email: longmazhanfeng@gmail.com
License: Apache License 2.0
Platform: UNKNOWN
Classifier: Environment :: Console
Classifier: Intended Audience :: Developers
Classifier: Operating System :: OS Independent
Classifier: Programming Language :: Python :: 2.7
